telgine/__init__.py
telgine/cli/__init__.py
telgine/cli/cli.py
telgine/cli/generate.py
telgine/cli/init.py
telgine/cli/migrate.py
telgine/core/__init__.py
telgine/core/app.py
telgine/core/ask_data_middleware.py
telgine/core/autoloader.py
telgine/core/bot.py
telgine/core/config.py
telgine/core/controller.py
telgine/core/controllers.py
telgine/core/ctx.py
telgine/core/db.py
telgine/core/filter_.py
telgine/core/functions.py
telgine/core/loader.py
telgine/core/middleware.py
telgine/core/model.py
telgine/core/register.py
telgine/core/scheduling.py
telgine/core/store.py
telgine/core/telgine_object.py
telgine/core/templates/__init__.py
telgine/core/templates/component.py
telgine/core/templates/example.xml
telgine/core/templates/keyboards.py
telgine/core/templates/lexer.py
telgine/core/templates/nodes.py
telgine/core/templates/parser.py
telgine/templates/model.txt
telgine/templates/project/.env
telgine/templates/project/.gitignore
telgine/templates/project/README.md
telgine/templates/project/bot/__init__.py
telgine/templates/project/bot/config/__init__.py
telgine/templates/project/bot/config/app.py
telgine/templates/project/bot/config/env.py
telgine/templates/project/bot/controllers/__init__.py
telgine/templates/project/bot/controllers/start.py
telgine/templates/project/bot/filters/__init__.py
telgine/templates/project/bot/locales/ru.json
telgine/templates/project/bot/middlewares/__init__.py
telgine/templates/project/bot/models/__init__.py
telgine/templates/project/bot/services/__init__.py
telgine/templates/project/bot/stores/User.py
telgine/templates/project/bot/stores/__init__.py
telgine/templates/project/bot/templates/__init__.py
telgine/templates/project/bot/templates/example.xml
telgine/templates/project/bot/templates/message.xml
telgine/templates/project/bot/types/__init__.py
telgine/templates/project/bot/utils/__init__.py
telgine/templates/project/main.py
telgine/templates/project/pyproject.toml
telgine/types/__init__.py
telgine/types/config.py
telgine-0.2.1.dist-info/entry_points.txt
telgine-0.2.1.dist-info/WHEEL
telgine-0.2.1.dist-info/METADATA
telgine-0.2.1.dist-info/RECORD
